<annotation>
	<folder></folder>
	<filename>00000187_jpg.rf.d91856d3ce61250297a3b8286710e362.jpg</filename>
	<path>00000187_jpg.rf.d91856d3ce61250297a3b8286710e362.jpg</path>
	<source>
		<database>roboflow.ai</database>
	</source>
	<size>
		<width>416</width>
		<height>416</height>
		<depth>3</depth>
	</size>
	<segmented>0</segmented>
	<object>
		<name>car</name>
		<pose>Unspecified</pose>
		<truncated>0</truncated>
		<difficult>0</difficult>
		<occluded>0</occluded>
		<bndbox>
			<xmin>45</xmin>
			<xmax>361</xmax>
			<ymin>89</ymin>
			<ymax>349</ymax>
		</bndbox>
	</object>
</annotation>
