<annotation>
	<folder></folder>
	<filename>00017869_jpg.rf.8e94bc76ffd776e1e7193308e7d3e62a.jpg</filename>
	<path>00017869_jpg.rf.8e94bc76ffd776e1e7193308e7d3e62a.jpg</path>
	<source>
		<database>roboflow.ai</database>
	</source>
	<size>
		<width>416</width>
		<height>416</height>
		<depth>3</depth>
	</size>
	<segmented>0</segmented>
	<object>
		<name>truck</name>
		<pose>Unspecified</pose>
		<truncated>0</truncated>
		<difficult>0</difficult>
		<occluded>0</occluded>
		<bndbox>
			<xmin>12</xmin>
			<xmax>375</xmax>
			<ymin>71</ymin>
			<ymax>355</ymax>
		</bndbox>
	</object>
</annotation>
