<annotation>
	<folder></folder>
	<filename>00019884_jpg.rf.e19caffd4a633471ef1adcfa5bdd514a.jpg</filename>
	<path>00019884_jpg.rf.e19caffd4a633471ef1adcfa5bdd514a.jpg</path>
	<source>
		<database>roboflow.ai</database>
	</source>
	<size>
		<width>416</width>
		<height>416</height>
		<depth>3</depth>
	</size>
	<segmented>0</segmented>
	<object>
		<name>truck</name>
		<pose>Unspecified</pose>
		<truncated>0</truncated>
		<difficult>0</difficult>
		<occluded>0</occluded>
		<bndbox>
			<xmin>17</xmin>
			<xmax>385</xmax>
			<ymin>56</ymin>
			<ymax>360</ymax>
		</bndbox>
	</object>
</annotation>
